<?xml version="1.0" encoding="utf-8"?>
<search>
  
  
  
  <entry>
    <title>今日份阿猫阿狗</title>
    <link href="/2022/11/21/%E4%BB%8A%E6%97%A5%E4%BB%BD%E9%98%BF%E7%8C%AB%E9%98%BF%E7%8B%97/"/>
    <url>/2022/11/21/%E4%BB%8A%E6%97%A5%E4%BB%BD%E9%98%BF%E7%8C%AB%E9%98%BF%E7%8B%97/</url>
    
    <content type="html"><![CDATA[<h1 id="神奇的动物在哪里"><a href="#神奇的动物在哪里" class="headerlink" title="神奇的动物在哪里"></a>神奇的动物在哪里</h1><h2 id="奇奇怪怪的阿猫"><a href="#奇奇怪怪的阿猫" class="headerlink" title="奇奇怪怪的阿猫"></a>奇奇怪怪的阿猫</h2><p><img src="/2022/11/21/%E4%BB%8A%E6%97%A5%E4%BB%BD%E9%98%BF%E7%8C%AB%E9%98%BF%E7%8B%97/OM_1669008983360.jpeg"><br><img src="/2022/11/21/%E4%BB%8A%E6%97%A5%E4%BB%BD%E9%98%BF%E7%8C%AB%E9%98%BF%E7%8B%97/OM_1669008983361.jpeg"><br><img src="/2022/11/21/%E4%BB%8A%E6%97%A5%E4%BB%BD%E9%98%BF%E7%8C%AB%E9%98%BF%E7%8B%97/OM_1669008983362.jpeg"><br><img src="/2022/11/21/%E4%BB%8A%E6%97%A5%E4%BB%BD%E9%98%BF%E7%8C%AB%E9%98%BF%E7%8B%97/OM_1669008983363.jpeg"><br><img src="/2022/11/21/%E4%BB%8A%E6%97%A5%E4%BB%BD%E9%98%BF%E7%8C%AB%E9%98%BF%E7%8B%97/OM_1669008983364.jpeg"><br><img src="/2022/11/21/%E4%BB%8A%E6%97%A5%E4%BB%BD%E9%98%BF%E7%8C%AB%E9%98%BF%E7%8B%97/OM_1669008983365.jpeg"><br><img src="/2022/11/21/%E4%BB%8A%E6%97%A5%E4%BB%BD%E9%98%BF%E7%8C%AB%E9%98%BF%E7%8B%97/OM_1669008983366.jpeg"><br><img src="/2022/11/21/%E4%BB%8A%E6%97%A5%E4%BB%BD%E9%98%BF%E7%8C%AB%E9%98%BF%E7%8B%97/OM_1669008983367.jpeg"></p>]]></content>
    
    
    <categories>
      
      <category>小动物</category>
      
    </categories>
    
    
    <tags>
      
      <tag>阿猫</tag>
      
    </tags>
    
  </entry>
  
  
  
  <entry>
    <title>珍藏旅行照片</title>
    <link href="/2022/11/21/%E7%8F%8D%E8%97%8F%E6%97%85%E8%A1%8C%E7%85%A7%E7%89%87/"/>
    <url>/2022/11/21/%E7%8F%8D%E8%97%8F%E6%97%85%E8%A1%8C%E7%85%A7%E7%89%87/</url>
    
    <content type="html"><![CDATA[<h1 id="世界那么大，总得去看看"><a href="#世界那么大，总得去看看" class="headerlink" title="世界那么大，总得去看看"></a>世界那么大，总得去看看</h1><h2 id="四川"><a href="#四川" class="headerlink" title="四川"></a>四川</h2><p><img src="/2022/11/21/%E7%8F%8D%E8%97%8F%E6%97%85%E8%A1%8C%E7%85%A7%E7%89%87/1.png"><br><img src="/2022/11/21/%E7%8F%8D%E8%97%8F%E6%97%85%E8%A1%8C%E7%85%A7%E7%89%87/2.jpg"><br><img src="/2022/11/21/%E7%8F%8D%E8%97%8F%E6%97%85%E8%A1%8C%E7%85%A7%E7%89%87/4.jpg"></p><h2 id="北京"><a href="#北京" class="headerlink" title="北京"></a>北京</h2><p><img src="/2022/11/21/%E7%8F%8D%E8%97%8F%E6%97%85%E8%A1%8C%E7%85%A7%E7%89%87/3.jpg"></p>]]></content>
    
    
    <categories>
      
      <category>旅行</category>
      
    </categories>
    
    
    <tags>
      
      <tag>My Wife</tag>
      
    </tags>
    
  </entry>
  
  
  
  
</search>
